snippet_converter/__init__.py
snippet_converter/cli.py
snippet_converter/setup.py
snippet_converter/sublime.py
snippet_converter-0.1a9.dist-info/LICENSE
snippet_converter-0.1a9.dist-info/METADATA
snippet_converter-0.1a9.dist-info/WHEEL
snippet_converter-0.1a9.dist-info/entry_points.txt
snippet_converter-0.1a9.dist-info/top_level.txt
snippet_converter-0.1a9.dist-info/RECORD
